arka_python_test/__init__.py
arka_python_test/api.py
tests/__init__.py
tests/test_arka.py
arka_python_test-0.1.dist-info/LICENSE
arka_python_test-0.1.dist-info/METADATA
arka_python_test-0.1.dist-info/WHEEL
arka_python_test-0.1.dist-info/top_level.txt
arka_python_test-0.1.dist-info/RECORD
